Metadata-Version: 2.1
Name: pyinstinct
Version: 0.0.1
Summary: Number guessing game to test your instinct power
Home-page: https://github.com/prahladyeri/pyinstinct
Author: Prahlad Yeri
Author-email: prahladyeri@yahoo.com
License: MIT
Keywords: security,scanner
Platform: UNKNOWN
Classifier: Programming Language :: Python :: 3
Classifier: License :: OSI Approved :: MIT License
Classifier: Operating System :: OS Independent
Requires-Python: >= 3.4
